miscellaneous/__init__.py
miscellaneous/search_molec_sdfs.py
miscellaneous-1.0.0.dist-info/DESCRIPTION.rst
miscellaneous-1.0.0.dist-info/METADATA
miscellaneous-1.0.0.dist-info/RECORD
miscellaneous-1.0.0.dist-info/WHEEL
miscellaneous-1.0.0.dist-info/metadata.json
miscellaneous-1.0.0.dist-info/top_level.txt
