Metadata-Version: 2.0
Name: miscellaneous
Version: 1.0.0
Summary: Retrieve analogs given a query molecule and a database.
Home-page: https://github.com/nostrumbiodiscovery/analogs_finder
Author: Daniel Soler
Author-email: daniel.soler@nostrumbiodiscovery.com
License: UNKNOWN
Platform: UNKNOWN
Classifier: Programming Language :: Python :: 3
Classifier: License :: OSI Approved :: MIT License
Classifier: Operating System :: OS Independent
Requires-Dist: tqdm
